<?xml version="1.0" encoding="utf-8"?><helpItems schema="maml">
<command:command xmlns:maml="http://schemas.microsoft.com/maml/2004/10" xmlns:command="http://schemas.microsoft.com/maml/dev/command/2004/10" xmlns:dev="http://schemas.microsoft.com/maml/dev/2004/10" xmlns:MSHelp="http://msdn.microsoft.com/mshelp">
<!--Generated by PS Cmdlet Help Editor-->
	<command:details>
		<command:name>Connect-AppSenseManagementServer</command:name>
		<maml:description>
			<maml:para>Connects to the specified AppSense Management Server.  All subsequent cmdlets will use this server for their operations.</maml:para>
		</maml:description>
		<maml:copyright>
			<maml:para />
		</maml:copyright>
		<command:verb>Connect</command:verb>
		<command:noun>AppSenseManagementServer</command:noun>
		<dev:version />
	</command:details>
	<maml:description>
		<maml:para>The Connect-AppSenseManagementServer cmdlet will create a connection to the specified AppSense Management Server using the provided credetials.  If no credentials are provided then the user will prompted to enter some.</maml:para>
	</maml:description>
	<command:syntax>
		<command:syntaxItem>
			<maml:name>Connect-AppSenseManagementServer</maml:name>
			<command:parameter required="true" variableLength="false" globbing="false" pipelineInput="false" position="named">
				<maml:name>Server</maml:name>
				<maml:description>
					<maml:para>Specifies name of the AppSense Management Server to connect to.  This can be either NetBIOS or FQDN.  Only the hostname is required.</maml:para>
				</maml:description>
				<command:parameterValue required="true" variableLength="false">String</command:parameterValue>
			</command:parameter>
			<command:parameter required="true" variableLength="false" globbing="false" pipelineInput="false" position="named">
				<maml:name>Credentials</maml:name>
				<maml:description>
					<maml:para>An object containing the credentials of a user to connect to the AppSense Management Server with.</maml:para>
				</maml:description>
				<command:parameterValue required="true" variableLength="false">PSCredential</command:parameterValue>
			</command:parameter>
			<command:parameter required="false" variableLength="false" globbing="false" pipelineInput="false" position="named">
				<maml:name>Port</maml:name>
				<maml:description>
					<maml:para>The port number to use when connecting to the Management Server</maml:para>
				</maml:description>
				<command:parameterValue required="true" variableLength="false">UInt32</command:parameterValue>
			</command:parameter>
			<command:parameter required="false" variableLength="false" globbing="false" pipelineInput="false" position="named">
				<maml:name>UseHTTPS</maml:name>
				<maml:description>
					<maml:para>When specified HTTPS will be used to connect to the Management Server</maml:para>
				</maml:description>
				<command:parameterValue required="false" variableLength="false">SwitchParameter</command:parameterValue>
			</command:parameter>
			<command:parameter required="false" variableLength="false" globbing="false" pipelineInput="false" position="named">
				<maml:name>TrackTime</maml:name>
				<maml:description>
					<maml:para>When provided the time will also be output to any verbosely written line.</maml:para>
				</maml:description>
				<command:parameterValue required="false" variableLength="false">SwitchParameter</command:parameterValue>
			</command:parameter>
		</command:syntaxItem>
		<command:syntaxItem>
			<maml:name>Connect-AppSenseManagementServer</maml:name>
			<command:parameter required="true" variableLength="false" globbing="false" pipelineInput="false" position="named">
				<maml:name>Server</maml:name>
				<maml:description>
					<maml:para>Specifies name of the AppSense Management Server to connect to.  This can be either NetBIOS or FQDN.  Only the hostname is required.</maml:para>
				</maml:description>
				<command:parameterValue required="true" variableLength="false">String</command:parameterValue>
			</command:parameter>
			<command:parameter required="false" variableLength="false" globbing="false" pipelineInput="false" position="named">
				<maml:name>Port</maml:name>
				<maml:description>
					<maml:para>The port number to use when connecting to the Management Server</maml:para>
				</maml:description>
				<command:parameterValue required="true" variableLength="false">UInt32</command:parameterValue>
			</command:parameter>
			<command:parameter required="false" variableLength="false" globbing="false" pipelineInput="false" position="named">
				<maml:name>UseHTTPS</maml:name>
				<maml:description>
					<maml:para>When specified HTTPS will be used to connect to the Management Server</maml:para>
				</maml:description>
				<command:parameterValue required="false" variableLength="false">SwitchParameter</command:parameterValue>
			</command:parameter>
			<command:parameter required="true" variableLength="false" globbing="false" pipelineInput="false" position="named">
				<maml:name>UseCurrentUser</maml:name>
				<maml:description>
					<maml:para>When supplied the cmdlet will use the credentials of the executing user in order to connect to the AppSense Management Server.</maml:para>
				</maml:description>
				<command:parameterValue required="false" variableLength="false">SwitchParameter</command:parameterValue>
			</command:parameter>
			<command:parameter required="false" variableLength="false" globbing="false" pipelineInput="false" position="named">
				<maml:name>TrackTime</maml:name>
				<maml:description>
					<maml:para>When provided the time will also be output to any verbosely written line.</maml:para>
				</maml:description>
				<command:parameterValue required="false" variableLength="false">SwitchParameter</command:parameterValue>
			</command:parameter>
		</command:syntaxItem>
	</command:syntax>
	<command:parameters>
		<command:parameter required="false" variableLength="false" globbing="false" pipelineInput="false" position="named">
			<maml:name>Port</maml:name>
			<maml:description>
				<maml:para>The port number to use when connecting to the Management Server</maml:para>
			</maml:description>
			<command:parameterValue required="true" variableLength="false">UInt32</command:parameterValue>
			<dev:type>
				<maml:name>UInt32</maml:name>
				<maml:uri/>
			</dev:type>
			<dev:defaultValue></dev:defaultValue>
		</command:parameter>
		<command:parameter required="false" variableLength="false" globbing="false" pipelineInput="false" position="named">
			<maml:name>UseHTTPS</maml:name>
			<maml:description>
				<maml:para>When specified HTTPS will be used to connect to the Management Server</maml:para>
			</maml:description>
			<command:parameterValue required="false" variableLength="false">SwitchParameter</command:parameterValue>
			<dev:type>
				<maml:name>SwitchParameter</maml:name>
				<maml:uri/>
			</dev:type>
			<dev:defaultValue></dev:defaultValue>
		</command:parameter>
		<command:parameter required="false" variableLength="false" globbing="false" pipelineInput="false" position="named">
			<maml:name>TrackTime</maml:name>
			<maml:description>
				<maml:para>When provided the time will also be output to any verbosely written line.</maml:para>
			</maml:description>
			<command:parameterValue required="false" variableLength="false">SwitchParameter</command:parameterValue>
			<dev:type>
				<maml:name>SwitchParameter</maml:name>
				<maml:uri/>
			</dev:type>
			<dev:defaultValue></dev:defaultValue>
		</command:parameter>
		<command:parameter required="true" variableLength="false" globbing="false" pipelineInput="false" position="named">
			<maml:name>UseCurrentUser</maml:name>
			<maml:description>
				<maml:para>When supplied the cmdlet will use the credentials of the executing user in order to connect to the AppSense Management Server.</maml:para>
			</maml:description>
			<command:parameterValue required="false" variableLength="false">SwitchParameter</command:parameterValue>
			<dev:type>
				<maml:name>SwitchParameter</maml:name>
				<maml:uri/>
			</dev:type>
			<dev:defaultValue></dev:defaultValue>
		</command:parameter>
		<command:parameter required="true" variableLength="false" globbing="false" pipelineInput="false" position="named">
			<maml:name>Server</maml:name>
			<maml:description>
				<maml:para>Specifies name of the AppSense Management Server to connect to.  This can be either NetBIOS or FQDN.  Only the hostname is required.</maml:para>
			</maml:description>
			<command:parameterValue required="true" variableLength="false">String</command:parameterValue>
			<dev:type>
				<maml:name>String</maml:name>
				<maml:uri/>
			</dev:type>
			<dev:defaultValue></dev:defaultValue>
		</command:parameter>
		<command:parameter required="true" variableLength="false" globbing="false" pipelineInput="false" position="named">
			<maml:name>Credentials</maml:name>
			<maml:description>
				<maml:para>An object containing the credentials of a user to connect to the AppSense Management Server with.</maml:para>
			</maml:description>
			<command:parameterValue required="true" variableLength="false">PSCredential</command:parameterValue>
			<dev:type>
				<maml:name>PSCredential</maml:name>
				<maml:uri/>
			</dev:type>
			<dev:defaultValue></dev:defaultValue>
		</command:parameter>
	</command:parameters>
	<command:inputTypes>
		<command:inputType>
			<dev:type>
				<maml:name>None</maml:name>
				<maml:uri></maml:uri>
				<maml:description/>
			</dev:type>
			<maml:description>
<maml:para />
			</maml:description>
		</command:inputType>
	</command:inputTypes>
	<command:returnValues>
		<command:returnValue>
			<dev:type>
				<maml:name>System.Boolean</maml:name>
				<maml:uri></maml:uri>
				<maml:description/>
			</dev:type>
			<maml:description>
				<maml:para>The cmdlet returns boolean false on failure or boolean true when a successful connection is made.</maml:para>
			</maml:description>
		</command:returnValue>
	</command:returnValues>
	<command:terminatingErrors></command:terminatingErrors>
	<command:nonTerminatingErrors></command:nonTerminatingErrors>
	<maml:alertSet>
		<maml:title></maml:title>
		<maml:alert>
			<maml:para />
		</maml:alert>
	</maml:alertSet>
	<command:examples>
		<command:example>
			<maml:title>--------------------------  Example 1  --------------------------</maml:title>
			<maml:introduction>
				<maml:paragraph>PS C:\&gt;</maml:paragraph>
			</maml:introduction>
			<dev:code>Connect-AppSenseManagementServer &quot;APS-MGMT-01&quot; -UseCurrentUser</dev:code>
			<dev:remarks>
				<maml:para>This example will use the credentials of the user executing the cmdlet to create a connection to the &quot;APS-MGMT-01&quot; server.</maml:para>
				<maml:para />
				<maml:para />
				<maml:para></maml:para>
			</dev:remarks>
			<command:commandLines>
				<command:commandLine>
					<command:commandText>
						<maml:para />
					</command:commandText>
				</command:commandLine>
			</command:commandLines>
		</command:example>
		<command:example>
			<maml:title>--------------------------  Example 2  --------------------------</maml:title>
			<maml:introduction>
				<maml:paragraph>PS C:\&gt;</maml:paragraph>
			</maml:introduction>
			<dev:code>Connect-AppSenseManagementServer &quot;APS-MGMT-01&quot; -Credentials (Get-Credential)</dev:code>
			<dev:remarks>
				<maml:para>This example will prompt the user to enter the credentials required for connecting to &quot;APS-MGMT-01&quot;.</maml:para>
				<maml:para />
				<maml:para />
				<maml:para></maml:para>
			</dev:remarks>
			<command:commandLines>
				<command:commandLine>
					<command:commandText>
						<maml:para />
					</command:commandText>
				</command:commandLine>
			</command:commandLines>
		</command:example>
	</command:examples>
	<maml:relatedLinks>
	</maml:relatedLinks>
</command:command>
<command:command xmlns:maml="http://schemas.microsoft.com/maml/2004/10" xmlns:command="http://schemas.microsoft.com/maml/dev/command/2004/10" xmlns:dev="http://schemas.microsoft.com/maml/dev/2004/10" xmlns:MSHelp="http://msdn.microsoft.com/mshelp">
<!--Generated by PS Cmdlet Help Editor-->
	<command:details>
		<command:name>Get-AppSenseManagementServerDetails</command:name>
		<maml:description>
			<maml:para>Retrieves information about the AppSense Management Server.</maml:para>
		</maml:description>
		<maml:copyright>
			<maml:para />
		</maml:copyright>
		<command:verb>Get</command:verb>
		<command:noun>AppSenseManagementServerDetails</command:noun>
		<dev:version />
	</command:details>
	<maml:description>
		<maml:para>The Get-AppSenseManagementServerDetails cmdlet retrieves information about the AppSense Management Server.  This information is the summary information that is normally found in the server details area of the AppSense Management Console.</maml:para>
	</maml:description>
	<command:syntax>
		<command:syntaxItem>
			<maml:name>Get-AppSenseManagementServerDetails</maml:name>
			<command:parameter required="false" variableLength="false" globbing="false" pipelineInput="false" position="named">
				<maml:name>TrackTime</maml:name>
				<maml:description>
					<maml:para>When provided the time will also be output to any verbosely written line.</maml:para>
				</maml:description>
				<command:parameterValue required="false" variableLength="false">SwitchParameter</command:parameterValue>
			</command:parameter>
		</command:syntaxItem>
	</command:syntax>
	<command:parameters>
		<command:parameter required="false" variableLength="false" globbing="false" pipelineInput="false" position="named">
			<maml:name>TrackTime</maml:name>
			<maml:description>
				<maml:para>When provided the time will also be output to any verbosely written line.</maml:para>
			</maml:description>
			<command:parameterValue required="false" variableLength="false">SwitchParameter</command:parameterValue>
			<dev:type>
				<maml:name>SwitchParameter</maml:name>
				<maml:uri/>
			</dev:type>
			<dev:defaultValue></dev:defaultValue>
		</command:parameter>
	</command:parameters>
	<command:inputTypes>
		<command:inputType>
			<dev:type>
				<maml:name>None</maml:name>
				<maml:uri></maml:uri>
				<maml:description/>
			</dev:type>
			<maml:description>
<maml:para />
			</maml:description>
		</command:inputType>
	</command:inputTypes>
	<command:returnValues>
		<command:returnValue>
			<dev:type>
				<maml:name>System.Boolean</maml:name>
				<maml:uri></maml:uri>
				<maml:description/>
			</dev:type>
			<maml:description>
				<maml:para>The cmdlet returns boolean false on failure.  If failure has occurred use the global PowerShell $error array to retrieve error information.</maml:para>
			</maml:description>
		</command:returnValue>
		<command:returnValue>
			<dev:type>
				<maml:name>ManagementConsole.DatabaseWebService.NamedValuesDataSet+NamedValuesRow[]</maml:name>
				<maml:uri />
				<maml:description/>
			</dev:type>
			<maml:description>
				<maml:para>
The cmdlet returns an enumerable dataset of key-value pairs on success.</maml:para>
			</maml:description>
		</command:returnValue>
	</command:returnValues>
	<command:terminatingErrors></command:terminatingErrors>
	<command:nonTerminatingErrors></command:nonTerminatingErrors>
	<maml:alertSet>
		<maml:title></maml:title>
		<maml:alert>
			<maml:para />
		</maml:alert>
	</maml:alertSet>
	<command:examples>
		<command:example>
			<maml:title>--------------------------  Example 1  --------------------------</maml:title>
			<maml:introduction>
				<maml:paragraph>PS C:\&gt;</maml:paragraph>
			</maml:introduction>
			<dev:code>(Get-AppSenseManagementServerDetails) | Where Name -eq &apos;SQL Server Version&apos;</dev:code>
			<dev:remarks>
				<maml:para>This example retrieves the information about the AppSense Management Server and then filters the result in order to get the &#39;SQL Server Version&#39; that connected database is using.</maml:para>
				<maml:para />
				<maml:para />
				<maml:para></maml:para>
			</dev:remarks>
			<command:commandLines>
				<command:commandLine>
					<command:commandText>
						<maml:para />
					</command:commandText>
				</command:commandLine>
			</command:commandLines>
		</command:example>
	</command:examples>
	<maml:relatedLinks>
	</maml:relatedLinks>
</command:command>
<command:command xmlns:maml="http://schemas.microsoft.com/maml/2004/10" xmlns:command="http://schemas.microsoft.com/maml/dev/command/2004/10" xmlns:dev="http://schemas.microsoft.com/maml/dev/2004/10" xmlns:MSHelp="http://msdn.microsoft.com/mshelp">
<!--Generated by PS Cmdlet Help Editor-->
	<command:details>
		<command:name>Get-AppSenseManagementServerName</command:name>
		<maml:description>
			<maml:para>Retrieves the name of the AppSense Management Server that you are currently connected to.</maml:para>
		</maml:description>
		<maml:copyright>
			<maml:para />
		</maml:copyright>
		<command:verb>Get</command:verb>
		<command:noun>AppSenseManagementServerName</command:noun>
		<dev:version />
	</command:details>
	<maml:description>
		<maml:para>The Get-AppSenseManagementServerName cmdlet retrieves the name of the AppSense Management Server that you are currently connected to.  This value is as it is stored in the AppSense Management Server Database.  This may differ from the name that you provided in the Connect-AppSenseManagementServer cmdlet.</maml:para>
	</maml:description>
	<command:syntax>
		<command:syntaxItem>
			<maml:name>Get-AppSenseManagementServerName</maml:name>
			<command:parameter required="false" variableLength="false" globbing="false" pipelineInput="false" position="named">
				<maml:name>TrackTime</maml:name>
				<maml:description>
					<maml:para>When provided the time will also be output to any verbosely written line.</maml:para>
				</maml:description>
				<command:parameterValue required="false" variableLength="false">SwitchParameter</command:parameterValue>
			</command:parameter>
		</command:syntaxItem>
	</command:syntax>
	<command:parameters>
		<command:parameter required="false" variableLength="false" globbing="false" pipelineInput="false" position="named">
			<maml:name>TrackTime</maml:name>
			<maml:description>
				<maml:para>When provided the time will also be output to any verbosely written line.</maml:para>
			</maml:description>
			<command:parameterValue required="false" variableLength="false">SwitchParameter</command:parameterValue>
			<dev:type>
				<maml:name>SwitchParameter</maml:name>
				<maml:uri/>
			</dev:type>
			<dev:defaultValue></dev:defaultValue>
		</command:parameter>
	</command:parameters>
	<command:inputTypes>
		<command:inputType>
			<dev:type>
				<maml:name>None</maml:name>
				<maml:uri></maml:uri>
				<maml:description/>
			</dev:type>
			<maml:description>
<maml:para />
			</maml:description>
		</command:inputType>
	</command:inputTypes>
	<command:returnValues>
		<command:returnValue>
			<dev:type>
				<maml:name>System.Boolean</maml:name>
				<maml:uri></maml:uri>
				<maml:description/>
			</dev:type>
			<maml:description>
				<maml:para>The cmdlet returns boolean false on failure.  If failure has occurred use the global PowerShell $error array to retrieve error information.</maml:para>
			</maml:description>
		</command:returnValue>
		<command:returnValue>
			<dev:type>
				<maml:name>System.String</maml:name>
				<maml:uri />
				<maml:description/>
			</dev:type>
			<maml:description>
				<maml:para>
The cmdlet returns a string containing the server name on success.</maml:para>
			</maml:description>
		</command:returnValue>
	</command:returnValues>
	<command:terminatingErrors></command:terminatingErrors>
	<command:nonTerminatingErrors></command:nonTerminatingErrors>
	<maml:alertSet>
		<maml:title></maml:title>
		<maml:alert>
			<maml:para />
		</maml:alert>
	</maml:alertSet>
	<command:examples>
	</command:examples>
	<maml:relatedLinks>
	</maml:relatedLinks>
</command:command>
<command:command xmlns:maml="http://schemas.microsoft.com/maml/2004/10" xmlns:command="http://schemas.microsoft.com/maml/dev/command/2004/10" xmlns:dev="http://schemas.microsoft.com/maml/dev/2004/10" xmlns:MSHelp="http://msdn.microsoft.com/mshelp">
<!--Generated by PS Cmdlet Help Editor-->
	<command:details>
		<command:name>Get-AppSenseManagementServerTimeZone</command:name>
		<maml:description>
			<maml:para />
		</maml:description>
		<maml:copyright>
			<maml:para />
		</maml:copyright>
		<command:verb>Get</command:verb>
		<command:noun>AppSenseManagementServerTimeZone</command:noun>
		<dev:version />
	</command:details>
	<maml:description>
		<maml:para />
	</maml:description>
	<command:syntax>
		<command:syntaxItem>
			<maml:name>Get-AppSenseManagementServerTimeZone</maml:name>
		</command:syntaxItem>
	</command:syntax>
	<command:parameters>	</command:parameters>
	<command:inputTypes>
		<command:inputType>
			<dev:type>
				<maml:name></maml:name>
				<maml:uri></maml:uri>
				<maml:description/>
			</dev:type>
			<maml:description>
<maml:para />
			</maml:description>
		</command:inputType>
	</command:inputTypes>
	<command:returnValues>
		<command:returnValue>
			<dev:type>
				<maml:name></maml:name>
				<maml:uri></maml:uri>
				<maml:description/>
			</dev:type>
			<maml:description>
<maml:para />
			</maml:description>
		</command:returnValue>
	</command:returnValues>
	<command:terminatingErrors></command:terminatingErrors>
	<command:nonTerminatingErrors></command:nonTerminatingErrors>
	<maml:alertSet>
		<maml:title></maml:title>
		<maml:alert>
			<maml:para />
		</maml:alert>
	</maml:alertSet>
	<command:examples>
	</command:examples>
	<maml:relatedLinks>
	</maml:relatedLinks>
</command:command>
<command:command xmlns:maml="http://schemas.microsoft.com/maml/2004/10" xmlns:command="http://schemas.microsoft.com/maml/dev/command/2004/10" xmlns:dev="http://schemas.microsoft.com/maml/dev/2004/10" xmlns:MSHelp="http://msdn.microsoft.com/mshelp">
<!--Generated by PS Cmdlet Help Editor-->
	<command:details>
		<command:name>Get-AppSenseManagementServerVersion</command:name>
		<maml:description>
			<maml:para>Retrieves the current version of the currently connected AppSense Management Server.</maml:para>
		</maml:description>
		<maml:copyright>
			<maml:para />
		</maml:copyright>
		<command:verb>Get</command:verb>
		<command:noun>AppSenseManagementServerVersion</command:noun>
		<dev:version />
	</command:details>
	<maml:description>
		<maml:para>The Get-AppSenseManagementServerVersion cmdlet retrieves the current version of the currently connected AppSense Management Server.</maml:para>
	</maml:description>
	<command:syntax>
		<command:syntaxItem>
			<maml:name>Get-AppSenseManagementServerVersion</maml:name>
			<command:parameter required="false" variableLength="false" globbing="false" pipelineInput="false" position="named">
				<maml:name>TrackTime</maml:name>
				<maml:description>
					<maml:para>When provided the time will also be output to any verbosely written line.</maml:para>
				</maml:description>
				<command:parameterValue required="false" variableLength="false">SwitchParameter</command:parameterValue>
			</command:parameter>
		</command:syntaxItem>
	</command:syntax>
	<command:parameters>
		<command:parameter required="false" variableLength="false" globbing="false" pipelineInput="false" position="named">
			<maml:name>TrackTime</maml:name>
			<maml:description>
				<maml:para>When provided the time will also be output to any verbosely written line.</maml:para>
			</maml:description>
			<command:parameterValue required="false" variableLength="false">SwitchParameter</command:parameterValue>
			<dev:type>
				<maml:name>SwitchParameter</maml:name>
				<maml:uri/>
			</dev:type>
			<dev:defaultValue></dev:defaultValue>
		</command:parameter>
	</command:parameters>
	<command:inputTypes>
		<command:inputType>
			<dev:type>
				<maml:name>None</maml:name>
				<maml:uri></maml:uri>
				<maml:description/>
			</dev:type>
			<maml:description>
<maml:para />
			</maml:description>
		</command:inputType>
	</command:inputTypes>
	<command:returnValues>
		<command:returnValue>
			<dev:type>
				<maml:name>System.Boolean</maml:name>
				<maml:uri></maml:uri>
				<maml:description/>
			</dev:type>
			<maml:description>
				<maml:para>
The cmdlet returns boolean false on failure.  If failure has occurred use the global PowerShell $error array to retrieve error information.</maml:para>
			</maml:description>
		</command:returnValue>
		<command:returnValue>
			<dev:type>
				<maml:name>System.String</maml:name>
				<maml:uri></maml:uri>
				<maml:description/>
			</dev:type>
			<maml:description>
				<maml:para>
The cmdlet returns a string containing the server version on success.</maml:para>
			</maml:description>
		</command:returnValue>
	</command:returnValues>
	<command:terminatingErrors></command:terminatingErrors>
	<command:nonTerminatingErrors></command:nonTerminatingErrors>
	<maml:alertSet>
		<maml:title></maml:title>
		<maml:alert>
			<maml:para />
		</maml:alert>
	</maml:alertSet>
	<command:examples>
		<command:example>
			<maml:title>--------------------------  Example 1  --------------------------</maml:title>
			<maml:introduction>
				<maml:paragraph>PS C:\&gt;</maml:paragraph>
			</maml:introduction>
			<dev:code>Get-AppSenseManagementServerVersion</dev:code>
			<dev:remarks>
				<maml:para>The example retrieves the version of the currently connected AppSense Management Server</maml:para>
				<maml:para />
				<maml:para />
				<maml:para></maml:para>
			</dev:remarks>
			<command:commandLines>
				<command:commandLine>
					<command:commandText>
						<maml:para />
					</command:commandText>
				</command:commandLine>
			</command:commandLines>
		</command:example>
	</command:examples>
	<maml:relatedLinks>
	</maml:relatedLinks>
</command:command>
<command:command xmlns:maml="http://schemas.microsoft.com/maml/2004/10" xmlns:command="http://schemas.microsoft.com/maml/dev/command/2004/10" xmlns:dev="http://schemas.microsoft.com/maml/dev/2004/10" xmlns:MSHelp="http://msdn.microsoft.com/mshelp">
<!--Generated by PS Cmdlet Help Editor-->
	<command:details>
		<command:name>Invoke-AppSenseManagementServerMethod</command:name>
		<maml:description>
			<maml:para>A pass-through cmdlet that allows an API method to be executed.</maml:para>
		</maml:description>
		<maml:copyright>
			<maml:para />
		</maml:copyright>
		<command:verb>Invoke</command:verb>
		<command:noun>AppSenseManagementServerMethod</command:noun>
		<dev:version />
	</command:details>
	<maml:description>
		<maml:para>The Invoke-AppSenseManagementServerMethod acts as a pass-through to the API methods available.</maml:para>
	</maml:description>
	<command:syntax>
		<command:syntaxItem>
			<maml:name>Invoke-AppSenseManagementServerMethod</maml:name>
			<command:parameter required="true" variableLength="false" globbing="false" pipelineInput="false" position="0">
				<maml:name>DataAccessEndpoint</maml:name>
				<maml:description>
					<maml:para>The name of the DataAccess Endpoint that the module can be found in</maml:para>
				</maml:description>
				<command:parameterValue required="true" variableLength="false">String</command:parameterValue>
			</command:parameter>
			<command:parameter required="true" variableLength="false" globbing="false" pipelineInput="false" position="1">
				<maml:name>MethodName</maml:name>
				<maml:description>
					<maml:para>The name of the method that should be executed</maml:para>
				</maml:description>
				<command:parameterValue required="true" variableLength="false">String</command:parameterValue>
			</command:parameter>
			<command:parameter required="false" variableLength="false" globbing="false" pipelineInput="false" position="2">
				<maml:name>MethodArguments</maml:name>
				<maml:description>
					<maml:para>The arguments to be passed to the specified method</maml:para>
				</maml:description>
				<command:parameterValue required="true" variableLength="false">Array</command:parameterValue>
			</command:parameter>
			<command:parameter required="false" variableLength="false" globbing="false" pipelineInput="false" position="named">
				<maml:name>TrackTime</maml:name>
				<maml:description>
					<maml:para>When provided the time will also be output to any verbosely written line.</maml:para>
				</maml:description>
				<command:parameterValue required="false" variableLength="false">SwitchParameter</command:parameterValue>
			</command:parameter>
		</command:syntaxItem>
	</command:syntax>
	<command:parameters>
		<command:parameter required="true" variableLength="false" globbing="false" pipelineInput="false" position="0">
			<maml:name>DataAccessEndpoint</maml:name>
			<maml:description>
				<maml:para>The name of the DataAccess Endpoint that the module can be found in</maml:para>
			</maml:description>
			<command:parameterValue required="true" variableLength="false">String</command:parameterValue>
			<dev:type>
				<maml:name>String</maml:name>
				<maml:uri/>
			</dev:type>
			<dev:defaultValue></dev:defaultValue>
		</command:parameter>
		<command:parameter required="true" variableLength="false" globbing="false" pipelineInput="false" position="1">
			<maml:name>MethodName</maml:name>
			<maml:description>
				<maml:para>The name of the method that should be executed</maml:para>
			</maml:description>
			<command:parameterValue required="true" variableLength="false">String</command:parameterValue>
			<dev:type>
				<maml:name>String</maml:name>
				<maml:uri/>
			</dev:type>
			<dev:defaultValue></dev:defaultValue>
		</command:parameter>
		<command:parameter required="false" variableLength="false" globbing="false" pipelineInput="false" position="named">
			<maml:name>TrackTime</maml:name>
			<maml:description>
				<maml:para>When provided the time will also be output to any verbosely written line.</maml:para>
			</maml:description>
			<command:parameterValue required="false" variableLength="false">SwitchParameter</command:parameterValue>
			<dev:type>
				<maml:name>SwitchParameter</maml:name>
				<maml:uri/>
			</dev:type>
			<dev:defaultValue></dev:defaultValue>
		</command:parameter>
		<command:parameter required="false" variableLength="false" globbing="false" pipelineInput="false" position="2">
			<maml:name>MethodArguments</maml:name>
			<maml:description>
				<maml:para>The arguments to be passed to the specified method</maml:para>
			</maml:description>
			<command:parameterValue required="true" variableLength="false">Array</command:parameterValue>
			<dev:type>
				<maml:name>Array</maml:name>
				<maml:uri/>
			</dev:type>
			<dev:defaultValue></dev:defaultValue>
		</command:parameter>
	</command:parameters>
	<command:inputTypes>
		<command:inputType>
			<dev:type>
				<maml:name>None</maml:name>
				<maml:uri></maml:uri>
				<maml:description/>
			</dev:type>
			<maml:description>
<maml:para />
			</maml:description>
		</command:inputType>
	</command:inputTypes>
	<command:returnValues>
		<command:returnValue>
			<dev:type>
				<maml:name>Mixed as per manual</maml:name>
				<maml:uri></maml:uri>
				<maml:description/>
			</dev:type>
			<maml:description>
				<maml:para>The cmdlet returns boolean false on failure.  If failure has occurred use the global PowerShell $error array to retrieve error information.  On success the return will be in the format for the API as described in the manual.</maml:para>
			</maml:description>
		</command:returnValue>
	</command:returnValues>
	<command:terminatingErrors></command:terminatingErrors>
	<command:nonTerminatingErrors></command:nonTerminatingErrors>
	<maml:alertSet>
		<maml:title></maml:title>
		<maml:alert>
			<maml:para />
		</maml:alert>
	</maml:alertSet>
	<command:examples>
		<command:example>
			<maml:title>--------------------------  Example 1  --------------------------</maml:title>
			<maml:introduction>
				<maml:paragraph>PS C:\&gt;</maml:paragraph>
			</maml:introduction>
			<dev:code>Invoke-AppSenseManagementServerMethod -DataAccessEndpoint Security -MethodName GetUsers</dev:code>
			<dev:remarks>
				<maml:para>This example shows calling the GetUsers method from the Security DataAccess Endpoint.  This method requires no arguments.  It will return a dataset in accordance with the API.</maml:para>
				<maml:para />
				<maml:para />
				<maml:para></maml:para>
			</dev:remarks>
			<command:commandLines>
				<command:commandLine>
					<command:commandText>
						<maml:para />
					</command:commandText>
				</command:commandLine>
			</command:commandLines>
		</command:example>
		<command:example>
			<maml:title>--------------------------  Example 2  --------------------------</maml:title>
			<maml:introduction>
				<maml:paragraph>PS C:\&gt;</maml:paragraph>
			</maml:introduction>
			<dev:code>Invoke-AppSenseManagementServerMethod -DataAccessEndpoint Machines -MethodName GetMachines -MethodArguments $false</dev:code>
			<dev:remarks>
				<maml:para>This example returns a dataset in accordance with the API that contains the machines registered in the Management Server.  It will pass the value $false to the method.</maml:para>
				<maml:para />
				<maml:para />
				<maml:para></maml:para>
			</dev:remarks>
			<command:commandLines>
				<command:commandLine>
					<command:commandText>
						<maml:para />
					</command:commandText>
				</command:commandLine>
			</command:commandLines>
		</command:example>
		<command:example>
			<maml:title>--------------------------  Example 3  --------------------------</maml:title>
			<maml:introduction>
				<maml:paragraph>PS C:\&gt;</maml:paragraph>
			</maml:introduction>
			<dev:code>Invoke-AppSenseManagementServerMethod -DataAccessEndpoint Groups -MethodName GetGroupFromKey -MethodArguments @(&quot;10A1CC29-DAFC-4850-A036-1A9956724A08&quot;, 0)</dev:code>
			<dev:remarks>
				<maml:para>This example will call the &quot;GetGroupFromKey&quot; method in the &quot;Groups&quot; DataAccessEndpoint passing multiple arguments into the method.</maml:para>
				<maml:para />
				<maml:para />
				<maml:para></maml:para>
			</dev:remarks>
			<command:commandLines>
				<command:commandLine>
					<command:commandText>
						<maml:para />
					</command:commandText>
				</command:commandLine>
			</command:commandLines>
		</command:example>
	</command:examples>
	<maml:relatedLinks>
	</maml:relatedLinks>
</command:command>
<command:command xmlns:maml="http://schemas.microsoft.com/maml/2004/10" xmlns:command="http://schemas.microsoft.com/maml/dev/command/2004/10" xmlns:dev="http://schemas.microsoft.com/maml/dev/2004/10" xmlns:MSHelp="http://msdn.microsoft.com/mshelp">
<!--Generated by PS Cmdlet Help Editor-->
	<command:details>
		<command:name>Set-AppSenseManagementServerTimeZone</command:name>
		<maml:description>
			<maml:para />
		</maml:description>
		<maml:copyright>
			<maml:para />
		</maml:copyright>
		<command:verb>Set</command:verb>
		<command:noun>AppSenseManagementServerTimeZone</command:noun>
		<dev:version />
	</command:details>
	<maml:description>
		<maml:para />
	</maml:description>
	<command:syntax>
		<command:syntaxItem>
			<maml:name>Set-AppSenseManagementServerTimeZone</maml:name>
			<command:parameter required="true" variableLength="false" globbing="false" pipelineInput="false" position="0">
				<maml:name>TimeZoneString</maml:name>
				<maml:description>
					<maml:para />
				</maml:description>
				<command:parameterValue required="true" variableLength="false">String</command:parameterValue>
			</command:parameter>
			<command:parameter required="false" variableLength="false" globbing="false" pipelineInput="false" position="named">
				<maml:name>TrackTime</maml:name>
				<maml:description>
					<maml:para />
				</maml:description>
				<command:parameterValue required="false" variableLength="false">SwitchParameter</command:parameterValue>
			</command:parameter>
		</command:syntaxItem>
	</command:syntax>
	<command:parameters>
		<command:parameter required="true" variableLength="false" globbing="false" pipelineInput="false" position="0">
			<maml:name>TimeZoneString</maml:name>
			<maml:description>
				<maml:para />
			</maml:description>
			<command:parameterValue required="true" variableLength="false">String</command:parameterValue>
			<dev:type>
				<maml:name>String</maml:name>
				<maml:uri/>
			</dev:type>
			<dev:defaultValue></dev:defaultValue>
		</command:parameter>
		<command:parameter required="false" variableLength="false" globbing="false" pipelineInput="false" position="named">
			<maml:name>TrackTime</maml:name>
			<maml:description>
				<maml:para />
			</maml:description>
			<command:parameterValue required="false" variableLength="false">SwitchParameter</command:parameterValue>
			<dev:type>
				<maml:name>SwitchParameter</maml:name>
				<maml:uri/>
			</dev:type>
			<dev:defaultValue></dev:defaultValue>
		</command:parameter>
	</command:parameters>
	<command:inputTypes>
		<command:inputType>
			<dev:type>
				<maml:name></maml:name>
				<maml:uri></maml:uri>
				<maml:description/>
			</dev:type>
			<maml:description>
<maml:para />
			</maml:description>
		</command:inputType>
	</command:inputTypes>
	<command:returnValues>
		<command:returnValue>
			<dev:type>
				<maml:name></maml:name>
				<maml:uri></maml:uri>
				<maml:description/>
			</dev:type>
			<maml:description>
<maml:para />
			</maml:description>
		</command:returnValue>
	</command:returnValues>
	<command:terminatingErrors></command:terminatingErrors>
	<command:nonTerminatingErrors></command:nonTerminatingErrors>
	<maml:alertSet>
		<maml:title></maml:title>
		<maml:alert>
			<maml:para />
		</maml:alert>
	</maml:alertSet>
	<command:examples>
		<command:example>
			<maml:title>--------------------------  Example 1  --------------------------</maml:title>
			<maml:introduction>
				<maml:paragraph>PS C:\&gt;</maml:paragraph>
			</maml:introduction>
			<dev:code>Set-AppSenseManagementServerTimeZone &apos;West Pacific Standard Time&apos;</dev:code>
			<dev:remarks>
				<maml:para>This example instructs all subsequent cmdlet to use the time zone when communicating with the connected AppSense Management Server.</maml:para>
				<maml:para />
				<maml:para />
				<maml:para></maml:para>
			</dev:remarks>
			<command:commandLines>
				<command:commandLine>
					<command:commandText>
						<maml:para />
					</command:commandText>
				</command:commandLine>
			</command:commandLines>
		</command:example>
	</command:examples>
	<maml:relatedLinks>
	</maml:relatedLinks>
</command:command>
</helpItems>